{
    "version": 3,
    "checkpoint": {
        "stack": "organization/ProductDeployer/user-1-stack",
        "latest": {
            "manifest": {
                "time": "2025-09-30T15:16:59.2618404+05:00",
                "magic": "e151377f41b4045974ddd5f40a88fe639ba8b472299593101102ef34d2330671",
                "version": "v3.197.0"
            },
            "secrets_providers": {
                "type": "passphrase",
                "state": {
                    "salt": "v1:VY50X2CrMu8=:v1:majOhpaQEAnXQ4Om:/dJl9brn6pil1rdNrH9b35n8xSFbKw=="
                }
            },
            "metadata": {}
        }
    }
}
